<?xml version="1.0" encoding="utf-8"?>
<TextureAtlas imagePath="spooky_kids_assets.png">
	<!-- Created with Adobe Animate version 19.1.0.349 -->
	<!-- http://www.adobe.com/products/animate.html -->
	<SubTexture name="spooky dance idle0000" x="0" y="0" width="492" height="549"/>
	<SubTexture name="spooky dance idle0001" x="0" y="0" width="492" height="549"/>
	<SubTexture name="spooky dance idle0002" x="492" y="0" width="492" height="549"/>
	<SubTexture name="spooky dance idle0003" x="492" y="0" width="492" height="549"/>
	<SubTexture name="spooky dance idle0004" x="984" y="0" width="492" height="549"/>
	<SubTexture name="spooky dance idle0005" x="984" y="0" width="492" height="549"/>
	<SubTexture name="spooky dance idle0006" x="1476" y="0" width="492" height="549"/>
	<SubTexture name="spooky dance idle0007" x="1476" y="0" width="492" height="549"/>
	<SubTexture name="spooky dance idle0008" x="1968" y="0" width="492" height="549"/>
	<SubTexture name="spooky dance idle0009" x="1968" y="0" width="492" height="549"/>
	<SubTexture name="spooky dance idle0010" x="2460" y="0" width="492" height="549"/>
	<SubTexture name="spooky dance idle0011" x="2460" y="0" width="492" height="549"/>
	<SubTexture name="spooky dance idle0012" x="984" y="0" width="492" height="549"/>
	<SubTexture name="spooky dance idle0013" x="984" y="0" width="492" height="549"/>
	<SubTexture name="spooky dance idle0014" x="1476" y="0" width="492" height="549"/>
	<SubTexture name="spooky dance idle0015" x="1476" y="0" width="492" height="549"/>
	<SubTexture name="spookyDown0000" x="0" y="549" width="463" height="412"/>
	<SubTexture name="spookyDown0001" x="0" y="549" width="463" height="412"/>
	<SubTexture name="spookyDown0002" x="463" y="549" width="463" height="412"/>
	<SubTexture name="spookyDown0003" x="463" y="549" width="463" height="412"/>
	<SubTexture name="spookyDown0004" x="463" y="549" width="463" height="412"/>
	<SubTexture name="spookyDown0005" x="463" y="549" width="463" height="412"/>
	<SubTexture name="spookyDown0006" x="463" y="549" width="463" height="412"/>
	<SubTexture name="spookyDown0007" x="463" y="549" width="463" height="412"/>
	<SubTexture name="spookyDown0008" x="463" y="549" width="463" height="412"/>
	<SubTexture name="spookyDown0009" x="463" y="549" width="463" height="412"/>
	<SubTexture name="spookyDown0010" x="463" y="549" width="463" height="412"/>
	<SubTexture name="spookyDown0011" x="463" y="549" width="463" height="412"/>
	<SubTexture name="spookyDown0012" x="463" y="549" width="463" height="412"/>
	<SubTexture name="spookyDown0013" x="463" y="549" width="463" height="412"/>
	<SubTexture name="spookyDown0014" x="463" y="549" width="463" height="412"/>
	<SubTexture name="spookyDown0015" x="463" y="549" width="463" height="412"/>
	<SubTexture name="spookyDown0016" x="463" y="549" width="463" height="412"/>
	<SubTexture name="spookyDown0017" x="463" y="549" width="463" height="412"/>
	<SubTexture name="spookyDown0018" x="463" y="549" width="463" height="412"/>
	<SubTexture name="spookyDown0019" x="463" y="549" width="463" height="412"/>
	<SubTexture name="spookyDown0020" x="463" y="549" width="463" height="412"/>
	<SubTexture name="spookyDown0021" x="463" y="549" width="463" height="412"/>
	<SubTexture name="spookyDown0022" x="463" y="549" width="463" height="412"/>
	<SubTexture name="spookyDown0023" x="463" y="549" width="463" height="412"/>
	<SubTexture name="spookyDown0024" x="463" y="549" width="463" height="412"/>
	<SubTexture name="spookyHey0000" x="926" y="549" width="641" height="529"/>
	<SubTexture name="spookyHey0001" x="926" y="549" width="641" height="529"/>
	<SubTexture name="spookyHey0002" x="1567" y="549" width="641" height="529"/>
	<SubTexture name="spookyHey0003" x="1567" y="549" width="641" height="529"/>
	<SubTexture name="spookyHey0004" x="2208" y="549" width="641" height="529"/>
	<SubTexture name="spookyHey0005" x="2208" y="549" width="641" height="529"/>
	<SubTexture name="spookyHey0006" x="0" y="1078" width="641" height="529"/>
	<SubTexture name="spookyHey0007" x="0" y="1078" width="641" height="529"/>
	<SubTexture name="spookyHey0008" x="0" y="1078" width="641" height="529"/>
	<SubTexture name="spookyHey0009" x="0" y="1078" width="641" height="529"/>
	<SubTexture name="spookyHey0010" x="0" y="1078" width="641" height="529"/>
	<SubTexture name="spookyHey0011" x="0" y="1078" width="641" height="529"/>
	<SubTexture name="spookyLeft0000" x="641" y="1078" width="564" height="531"/>
	<SubTexture name="spookyLeft0001" x="641" y="1078" width="564" height="531"/>
	<SubTexture name="spookyLeft0002" x="1205" y="1078" width="564" height="531"/>
	<SubTexture name="spookyLeft0003" x="1205" y="1078" width="564" height="531"/>
	<SubTexture name="spookyLeft0004" x="1205" y="1078" width="564" height="531"/>
	<SubTexture name="spookyLeft0005" x="1205" y="1078" width="564" height="531"/>
	<SubTexture name="spookyLeft0006" x="1205" y="1078" width="564" height="531"/>
	<SubTexture name="spookyLeft0007" x="1205" y="1078" width="564" height="531"/>
	<SubTexture name="spookyLeft0008" x="1205" y="1078" width="564" height="531"/>
	<SubTexture name="spookyLeft0009" x="1205" y="1078" width="564" height="531"/>
	<SubTexture name="spookyLeft0010" x="1205" y="1078" width="564" height="531"/>
	<SubTexture name="spookyLeft0011" x="1205" y="1078" width="564" height="531"/>
	<SubTexture name="spookyLeft0012" x="1205" y="1078" width="564" height="531"/>
	<SubTexture name="spookyLeft0013" x="1205" y="1078" width="564" height="531"/>
	<SubTexture name="spookyLeft0014" x="1205" y="1078" width="564" height="531"/>
	<SubTexture name="spookyMissDown0000" x="1769" y="1078" width="463" height="412"/>
	<SubTexture name="spookyMissDown0001" x="1769" y="1078" width="463" height="412"/>
	<SubTexture name="spookyMissDown0002" x="2232" y="1078" width="463" height="412"/>
	<SubTexture name="spookyMissDown0003" x="2232" y="1078" width="463" height="412"/>
	<SubTexture name="spookyMissDown0004" x="2232" y="1078" width="463" height="412"/>
	<SubTexture name="spookyMissDown0005" x="2232" y="1078" width="463" height="412"/>
	<SubTexture name="spookyMissDown0006" x="2232" y="1078" width="463" height="412"/>
	<SubTexture name="spookyMissDown0007" x="2232" y="1078" width="463" height="412"/>
	<SubTexture name="spookyMissDown0008" x="2232" y="1078" width="463" height="412"/>
	<SubTexture name="spookyMissDown0009" x="2232" y="1078" width="463" height="412"/>
	<SubTexture name="spookyMissDown0010" x="2232" y="1078" width="463" height="412"/>
	<SubTexture name="spookyMissDown0011" x="2232" y="1078" width="463" height="412"/>
	<SubTexture name="spookyMissDown0012" x="2232" y="1078" width="463" height="412"/>
	<SubTexture name="spookyMissDown0013" x="2232" y="1078" width="463" height="412"/>
	<SubTexture name="spookyMissDown0014" x="2232" y="1078" width="463" height="412"/>
	<SubTexture name="spookyMissDown0015" x="2232" y="1078" width="463" height="412"/>
	<SubTexture name="spookyMissDown0016" x="2232" y="1078" width="463" height="412"/>
	<SubTexture name="spookyMissDown0017" x="2232" y="1078" width="463" height="412"/>
	<SubTexture name="spookyMissDown0018" x="2232" y="1078" width="463" height="412"/>
	<SubTexture name="spookyMissDown0019" x="2232" y="1078" width="463" height="412"/>
	<SubTexture name="spookyMissDown0020" x="2232" y="1078" width="463" height="412"/>
	<SubTexture name="spookyMissDown0021" x="2232" y="1078" width="463" height="412"/>
	<SubTexture name="spookyMissDown0022" x="2232" y="1078" width="463" height="412"/>
	<SubTexture name="spookyMissDown0023" x="2232" y="1078" width="463" height="412"/>
	<SubTexture name="spookyMissDown0024" x="2232" y="1078" width="463" height="412"/>
	<SubTexture name="spookyMissLeft0000" x="0" y="1609" width="569" height="533"/>
	<SubTexture name="spookyMissLeft0001" x="0" y="1609" width="569" height="533"/>
	<SubTexture name="spookyMissLeft0002" x="569" y="1609" width="569" height="533"/>
	<SubTexture name="spookyMissLeft0003" x="569" y="1609" width="569" height="533"/>
	<SubTexture name="spookyMissLeft0004" x="569" y="1609" width="569" height="533"/>
	<SubTexture name="spookyMissLeft0005" x="569" y="1609" width="569" height="533"/>
	<SubTexture name="spookyMissLeft0006" x="569" y="1609" width="569" height="533"/>
	<SubTexture name="spookyMissLeft0007" x="569" y="1609" width="569" height="533"/>
	<SubTexture name="spookyMissLeft0008" x="569" y="1609" width="569" height="533"/>
	<SubTexture name="spookyMissLeft0009" x="569" y="1609" width="569" height="533"/>
	<SubTexture name="spookyMissLeft0010" x="569" y="1609" width="569" height="533"/>
	<SubTexture name="spookyMissLeft0011" x="569" y="1609" width="569" height="533"/>
	<SubTexture name="spookyMissLeft0012" x="569" y="1609" width="569" height="533"/>
	<SubTexture name="spookyMissLeft0013" x="569" y="1609" width="569" height="533"/>
	<SubTexture name="spookyMissLeft0014" x="569" y="1609" width="569" height="533"/>
	<SubTexture name="spookyMissRight0000" x="1138" y="1609" width="442" height="533"/>
	<SubTexture name="spookyMissRight0001" x="1138" y="1609" width="442" height="533"/>
	<SubTexture name="spookyMissRight0002" x="1580" y="1609" width="442" height="533"/>
	<SubTexture name="spookyMissRight0003" x="1580" y="1609" width="442" height="533"/>
	<SubTexture name="spookyMissRight0004" x="1580" y="1609" width="442" height="533"/>
	<SubTexture name="spookyMissRight0005" x="1580" y="1609" width="442" height="533"/>
	<SubTexture name="spookyMissRight0006" x="1580" y="1609" width="442" height="533"/>
	<SubTexture name="spookyMissRight0007" x="1580" y="1609" width="442" height="533"/>
	<SubTexture name="spookyMissRight0008" x="1580" y="1609" width="442" height="533"/>
	<SubTexture name="spookyMissRight0009" x="1580" y="1609" width="442" height="533"/>
	<SubTexture name="spookyMissRight0010" x="1580" y="1609" width="442" height="533"/>
	<SubTexture name="spookyMissRight0011" x="1580" y="1609" width="442" height="533"/>
	<SubTexture name="spookyMissRight0012" x="1580" y="1609" width="442" height="533"/>
	<SubTexture name="spookyMissRight0013" x="1580" y="1609" width="442" height="533"/>
	<SubTexture name="spookyMissRight0014" x="1580" y="1609" width="442" height="533"/>
	<SubTexture name="spookyMissRight0015" x="1580" y="1609" width="442" height="533"/>
	<SubTexture name="spookyMissRight0016" x="1580" y="1609" width="442" height="533"/>
	<SubTexture name="spookyMissRight0017" x="1580" y="1609" width="442" height="533"/>
	<SubTexture name="spookyMissRight0018" x="1580" y="1609" width="442" height="533"/>
	<SubTexture name="spookyMissRight0019" x="1580" y="1609" width="442" height="533"/>
	<SubTexture name="spookyMissRight0020" x="1580" y="1609" width="442" height="533"/>
	<SubTexture name="spookyMissRight0021" x="1580" y="1609" width="442" height="533"/>
	<SubTexture name="spookyMissRight0022" x="1580" y="1609" width="442" height="533"/>
	<SubTexture name="spookyMissRight0023" x="1580" y="1609" width="442" height="533"/>
	<SubTexture name="spookyMissRight0024" x="1580" y="1609" width="442" height="533"/>
	<SubTexture name="spookyMissUP0000" x="2022" y="1609" width="466" height="571"/>
	<SubTexture name="spookyMissUP0001" x="2022" y="1609" width="466" height="571"/>
	<SubTexture name="spookyMissUP0002" x="2488" y="1609" width="466" height="571"/>
	<SubTexture name="spookyMissUP0003" x="2488" y="1609" width="466" height="571"/>
	<SubTexture name="spookyMissUP0004" x="2488" y="1609" width="466" height="571"/>
	<SubTexture name="spookyRight0000" x="0" y="2180" width="442" height="533"/>
	<SubTexture name="spookyRight0001" x="0" y="2180" width="442" height="533"/>
	<SubTexture name="spookyRight0002" x="442" y="2180" width="442" height="533"/>
	<SubTexture name="spookyRight0003" x="442" y="2180" width="442" height="533"/>
	<SubTexture name="spookyRight0004" x="442" y="2180" width="442" height="533"/>
	<SubTexture name="spookyRight0005" x="442" y="2180" width="442" height="533"/>
	<SubTexture name="spookyRight0006" x="442" y="2180" width="442" height="533"/>
	<SubTexture name="spookyRight0007" x="442" y="2180" width="442" height="533"/>
	<SubTexture name="spookyRight0008" x="442" y="2180" width="442" height="533"/>
	<SubTexture name="spookyRight0009" x="442" y="2180" width="442" height="533"/>
	<SubTexture name="spookyRight0010" x="442" y="2180" width="442" height="533"/>
	<SubTexture name="spookyRight0011" x="442" y="2180" width="442" height="533"/>
	<SubTexture name="spookyRight0012" x="442" y="2180" width="442" height="533"/>
	<SubTexture name="spookyRight0013" x="442" y="2180" width="442" height="533"/>
	<SubTexture name="spookyRight0014" x="442" y="2180" width="442" height="533"/>
	<SubTexture name="spookyRight0015" x="442" y="2180" width="442" height="533"/>
	<SubTexture name="spookyRight0016" x="442" y="2180" width="442" height="533"/>
	<SubTexture name="spookyRight0017" x="442" y="2180" width="442" height="533"/>
	<SubTexture name="spookyRight0018" x="442" y="2180" width="442" height="533"/>
	<SubTexture name="spookyRight0019" x="442" y="2180" width="442" height="533"/>
	<SubTexture name="spookyRight0020" x="442" y="2180" width="442" height="533"/>
	<SubTexture name="spookyRight0021" x="442" y="2180" width="442" height="533"/>
	<SubTexture name="spookyRight0022" x="442" y="2180" width="442" height="533"/>
	<SubTexture name="spookyRight0023" x="442" y="2180" width="442" height="533"/>
	<SubTexture name="spookyRight0024" x="442" y="2180" width="442" height="533"/>
	<SubTexture name="spookyUp0000" x="884" y="2180" width="406" height="571"/>
	<SubTexture name="spookyUp0001" x="884" y="2180" width="406" height="571"/>
	<SubTexture name="spookyUp0002" x="1290" y="2180" width="406" height="571"/>
	<SubTexture name="spookyUp0003" x="1290" y="2180" width="406" height="571"/>
	<SubTexture name="spookyUp0004" x="1290" y="2180" width="406" height="571"/>
</TextureAtlas>
